{
  "$schema": "http://json-schema.org/draft-07/schema#",
  "$id": "s129-accessor-keyword",
  "title": "AccessorKeywordNode",
  "description": "AccessorKeyword AST 节点 (SyntaxKind: 129)",
  "allOf": [
    {
      "$ref": "base-token-node"
    },
    {
      "type": "object",
      "properties": {
        "kind": {
          "const": 129,
          "description": "语法种类：AccessorKeyword"
        }
      },
      "required": []
    }
  ],
  "metadata": {
    "category": "tokens",
    "syntaxKind": 129,
    "syntaxName": "AccessorKeyword",
    "baseType": "BaseTokenNode"
  }
}