{
  "$schema": "http://json-schema.org/draft-07/schema#",
  "$id": "s151-object-keyword",
  "title": "ObjectKeywordNode",
  "description": "ObjectKeyword AST 节点 (SyntaxKind: 151)",
  "allOf": [
    {
      "$ref": "../base/base-token-node"
    },
    {
      "type": "object",
      "properties": {
        "kind": {
          "const": 151,
          "description": "语法种类：ObjectKeyword"
        }
      },
      "required": []
    }
  ],
  "metadata": {
    "category": "tokens",
    "syntaxKind": 151,
    "syntaxName": "ObjectKeyword",
    "baseType": "BaseTokenNode",
    "generated": true,
    "conversion": {
      "children": {},
      "properties": {},
      "fromASTNode": {},
      "fromTsNode": {}
    }
  }
}